README.md
setup.cfg
setup.py
nextbus_client/__init__.py
nextbus_client/agency.py
nextbus_client/client.py
nextbus_client/errors.py
nextbus_client/predictions.py
nextbus_client/route.py
nextbus_client/route_config.py
nextbus_client/utilities.py
nextbus_client/version.py
nextbus_client.egg-info/PKG-INFO
nextbus_client.egg-info/SOURCES.txt
nextbus_client.egg-info/dependency_links.txt
nextbus_client.egg-info/requires.txt
nextbus_client.egg-info/top_level.txt