Metadata-Version: 1.1
Name: nextbus-client
Version: 0.1.1
Summary: Python3 compatible client for the NextBus public XML feed
Home-page: https://github.com/compybara/nextbus_client
Author: Adam Duston
Author-email: compybara@protonmail.com
License: BSD-3-Clause
Platform: UNKNOWN
Classifier: Intended Audience :: Developers
Classifier: Development Status :: 3 - Alpha
Classifier: License :: OSI Approved :: BSD License
Classifier: Operating System :: POSIX :: Linux
Classifier: Programming Language :: Python :: 3.5
Classifier: Programming Language :: Python :: 3.6
Classifier: Programming Language :: Python :: 3 :: Only
